logview_core/__init__.py
logview_core/handler.py
logview_core-2.3.0.dist-info/METADATA
logview_core-2.3.0.dist-info/WHEEL
logview_core-2.3.0.dist-info/top_level.txt
logview_core-2.3.0.dist-info/RECORD
