Metadata-Version: 2.1
Name: logview-core
Version: 2.3.0
Summary: A modern Python web framework designed to simplify your development process.
Home-page: https://github.com/Utsavch189/LogView-Main
Author: Utsav Chatterjee
Author-email: utsavchatterjee71@gmail.com
License: MIT
Platform: UNKNOWN
Classifier: License :: OSI Approved :: MIT License
Classifier: Programming Language :: Python :: 3.10
Classifier: Operating System :: OS Independent
Requires-Python: >=3.10
Requires-Dist: msgpack (==1.1.0)
Requires-Dist: requests (==2.32.3)
